synapses/__init__.py
synapses/perceptron.py
preceptron_pypi_om-0.0.2.dist-info/LICENSE
preceptron_pypi_om-0.0.2.dist-info/METADATA
preceptron_pypi_om-0.0.2.dist-info/WHEEL
preceptron_pypi_om-0.0.2.dist-info/top_level.txt
preceptron_pypi_om-0.0.2.dist-info/RECORD
